pysher/__init__.py
pysher/channel.py
pysher/connection.py
pysher/pusher.py
infomaniakpysher-0.0.1.dist-info/LICENSE
infomaniakpysher-0.0.1.dist-info/METADATA
infomaniakpysher-0.0.1.dist-info/WHEEL
infomaniakpysher-0.0.1.dist-info/top_level.txt
infomaniakpysher-0.0.1.dist-info/RECORD
