Metadata-Version: 2.1
Name: infomaniakpysher
Version: 0.0.1
Summary: Pusher websocket client for python, based on Erik Kulyk's PythonPusherClient
Home-page: https://github.com/deepbrook/Pysher
Author: Nils Diefenbach
Author-email: nlsdfnbch.foss@kolabnow.com
License: MIT
Keywords: pusher websocket client
Classifier: Development Status :: 4 - Beta
Classifier: Environment :: Web Environment
Classifier: License :: OSI Approved :: MIT License
Classifier: Programming Language :: Python
Classifier: Programming Language :: Python :: 3.5
Classifier: Programming Language :: Python :: 3.6
Classifier: Programming Language :: Python :: 3.7
Classifier: Topic :: Internet
Classifier: Topic :: Software Development :: Libraries 
Classifier: Topic :: Software Development :: Libraries :: Python Modules
License-File: LICENSE
Requires-Dist: websocket-client (!=0.49)
Requires-Dist: requests (>=2.26.0)
